metro2/__init__.py
metro2/ruby/index.rb
metro2-2.0.1.dist-info/LICENSE
metro2-2.0.1.dist-info/METADATA
metro2-2.0.1.dist-info/WHEEL
metro2-2.0.1.dist-info/top_level.txt
metro2-2.0.1.dist-info/RECORD
