Metadata-Version: 2.1
Name: metro2
Version: 2.0.1
Summary: Generate metro 2 format for credit reporting to credit bureaus
Home-page: https://gitlab.com/ranupeachstreet/metro2
Author: Ranu Lathi
Author-email: ranu@peachstreet.com
License: MIT
Platform: UNKNOWN
